{
    "root_path": "base-model",
    "model_path": "base-model",
    "logdir": "logs",
    "max_num_per_seq": 100,
    "seq_len": 100,
    "tree_path": "agp-data/172446_from_158713_insertion_tree.relabelled.tre",
    "table_path": "agp-data/172446_feature-table.biom",
    "metadata_path": "agp-data/agp-metadata.txt",
    "num_enc_layers": 1, 
    "dff": 128,
    "lstm_seq_out": 32,
    "dropout": 0.50,
    "batch_size": 32,
    "epochs": 10000,
    "patience": 1000, 
    "train_percent":0.7,
    "s_type": "gut",
    "mini_epochs": 5,
    "use_ema": true,
    "ema_momentum": 0.99,
    "num_samples": 200,
    "pred_pcoa_path": "agp-data/pred_pcoa.pcoa",
    "true_pcoa_path": "agp-data/true_pcoa.pcoa",
    "repeat": 5
}
